joist/__init__.py
joist/apps.py
joist/models.py
joist/settings.py
joist/signals.py
joist/urls.py
joist/views.py
joist/widgets.py
joist/static/joist/joist.js
joist/templates/joist/s3adminfileinput.html
joist/templates/joist/s3fileinput.html
joist-0.0.2.dist-info/LICENSE
joist-0.0.2.dist-info/METADATA
joist-0.0.2.dist-info/WHEEL
joist-0.0.2.dist-info/top_level.txt
joist-0.0.2.dist-info/RECORD
