Metadata-Version: 2.1
Name: joist
Version: 0.0.2
Summary: A django widget library for direct S3 uploads
Home-page: https://github.com/danlamanna/joist
Author: Kitware, Inc.
Author-email: kitware@kitware.com
License: Apache 2.0
Keywords: django,s3,django-widget
Platform: UNKNOWN
Classifier: Development Status :: 3 - Alpha
Classifier: Environment :: Web Environment
Classifier: License :: OSI Approved :: Apache Software License
Classifier: Operating System :: OS Independent
Classifier: Programming Language :: Python
Classifier: Programming Language :: Python :: 3
Classifier: Programming Language :: Python :: 3.7
Classifier: Programming Language :: Python :: 3.8
Requires-Python: >=3.7.0
Requires-Dist: django
Requires-Dist: django-storages
Requires-Dist: boto3
Requires-Dist: djangorestframework
